src/felhantering_karluk/__init__.py
src/felhantering_karluk/felhantering.py
cim_python_karluk-0.0.1.dist-info/METADATA
cim_python_karluk-0.0.1.dist-info/WHEEL
cim_python_karluk-0.0.1.dist-info/licenses/LICENSE
cim_python_karluk-0.0.1.dist-info/RECORD
