Metadata-Version: 2.1
Name: CIM_Python_Karluk
Version: 0.0.1
Summary: A small package to check user input values
Project-URL: Homepage, https://wikipedia.com
Project-URL: Bug Tracker, https://wikipedia.com
Author-email: Viktor Karluk <viktor.karluk@bredband.net>
License: Copyright (c) [2022] [Viktor Karluk]
License-File: LICENSE
Classifier: License :: OSI Approved :: MIT License
Classifier: Operating System :: OS Independent
Classifier: Programming Language :: Python :: 3
Requires-Python: >=3.7
